autopilot_tools/__init__.py
autopilot_tools/analyzer.py
autopilot_tools/configurator.py
autopilot_tools/enums.py
autopilot_tools/exceptions.py
autopilot_tools/mavlink_interface.py
autopilot_tools/mavlink_params.py
autopilot_tools/mission_interface.py
autopilot_tools/parameters.py
autopilot_tools/test_scenario.py
autopilot_tools/utils.py
autopilot_tools/vehicle.py
autopilot_tools/log_analyzer/__init__.py
autopilot_tools/log_analyzer/airspeed.py
autopilot_tools/log_analyzer/altitude.py
autopilot_tools/log_analyzer/color_logging.py
autopilot_tools/log_analyzer/device_id_parser.py
autopilot_tools/log_analyzer/esc_status.py
autopilot_tools/log_analyzer/extract.py
autopilot_tools/log_analyzer/flight_distance.py
autopilot_tools/log_analyzer/ice.py
autopilot_tools/log_analyzer/uorb_topics.py
autopilot_tools/log_analyzer/utils.py
autopilot_tools/mavlink_ftp/__init__.py
autopilot_tools/mavlink_ftp/ftp_filesystem.py
autopilot_tools/mavlink_ftp/mavftputils.py
autopilot_tools/mission_file/__init__.py
autopilot_tools/mission_file/mission_file.py
autopilot_tools/mission_file/mission_result.py
autopilot_tools/px4/__init__.py
autopilot_tools/px4/_px_uploader.py
autopilot_tools/px4/firmware_uploader.py
autopilot_tools/px4/px4_utils.py
autopilot_tools-0.5.4.dist-info/LICENSE
autopilot_tools-0.5.4.dist-info/METADATA
autopilot_tools-0.5.4.dist-info/WHEEL
autopilot_tools-0.5.4.dist-info/entry_points.txt
autopilot_tools-0.5.4.dist-info/top_level.txt
autopilot_tools-0.5.4.dist-info/RECORD
