Metadata-Version: 2.2
Name: autopilot_tools
Version: 0.5.4
Summary: PX4/ArduPilot autopilot tools
Author-email: Dmitry Ponomarev <PonomarevDA96@gmail.com>
Project-URL: Homepage, https://github.com/PonomarevDA/autopilot_tools
Project-URL: Bug Tracker, https://github.com/PonomarevDA/autopilot_tools/issues
Classifier: Programming Language :: Python :: 3
Classifier: License :: OSI Approved :: GNU General Public License v3 (GPLv3)
Classifier: Operating System :: OS Independent
Requires-Python: >=3.7
License-File: LICENSE
Requires-Dist: matplotlib
Requires-Dist: pytest
Requires-Dist: pyyaml
Requires-Dist: pyserial
Requires-Dist: pymavlink
Requires-Dist: tqdm
Requires-Dist: argparse
Requires-Dist: requests
Requires-Dist: numpy
Requires-Dist: six
Requires-Dist: StrEnum
